<?xml version="1.0"?>
<FREEALGEBRA createdAt="2014-01-02" createdBy="levandov">
  <vars>h,H2,H1,y6,y5,y4,y3,y2,y1,x6,x5,x4,x3,x2,x1</vars>
  <uptoDeg>7</uptoDeg>
  <basis>
		<ncpoly>x2*x1-x1*x2-x3*h</ncpoly>
		<ncpoly>x3*x1-x1*x3-2*x4*h</ncpoly>
		<ncpoly>x4*x1-x1*x4-3*x5*h</ncpoly>
		<ncpoly>x5*x1-x1*x5</ncpoly>
		<ncpoly>x6*x1-x1*x6</ncpoly>
		<ncpoly>y1*x1-x1*y1+H1*h</ncpoly>
		<ncpoly>y2*x1-x1*y2</ncpoly>
		<ncpoly>y3*x1-x1*y3+3*y2*h</ncpoly>
		<ncpoly>y4*x1-x1*y4+2*y3*h</ncpoly>
		<ncpoly>y5*x1-x1*y5+y4*h</ncpoly>
		<ncpoly>y6*x1-x1*y6</ncpoly>
		<ncpoly>H1*x1-x1*H1-2*x1*h</ncpoly>
		<ncpoly>H2*x1-x1*H2+x1*h</ncpoly>
		<ncpoly>h*x1-x1*h</ncpoly>
		<ncpoly>x3*x2-x2*x3</ncpoly>
		<ncpoly>x4*x2-x2*x4</ncpoly>
		<ncpoly>x5*x2-x2*x5-x6*h</ncpoly>
		<ncpoly>x6*x2-x2*x6</ncpoly>
		<ncpoly>y1*x2-x2*y1</ncpoly>
		<ncpoly>y2*x2-x2*y2+H2*h</ncpoly>
		<ncpoly>y3*x2-x2*y3-y1*h</ncpoly>
		<ncpoly>y4*x2-x2*y4</ncpoly>
		<ncpoly>y5*x2-x2*y5</ncpoly>
		<ncpoly>y6*x2-x2*y6+y5*h</ncpoly>
		<ncpoly>H1*x2-x2*H1+3*x2*h</ncpoly>
		<ncpoly>H2*x2-x2*H2-2*x2*h</ncpoly>
		<ncpoly>h*x2-x2*h</ncpoly>
		<ncpoly>x4*x3-x3*x4+3*x6*h</ncpoly>
		<ncpoly>x5*x3-x3*x5</ncpoly>
		<ncpoly>x6*x3-x3*x6</ncpoly>
		<ncpoly>y1*x3-x3*y1+3*x2*h</ncpoly>
		<ncpoly>y2*x3-x3*y2-x1*h</ncpoly>
		<ncpoly>y3*x3-x3*y3+H1*h+3*H2*h</ncpoly>
		<ncpoly>y4*x3-x3*y4-2*y1*h</ncpoly>
		<ncpoly>y5*x3-x3*y5</ncpoly>
		<ncpoly>y6*x3-x3*y6-y4*h</ncpoly>
		<ncpoly>H1*x3-x3*H1+x3*h</ncpoly>
		<ncpoly>H2*x3-x3*H2-x3*h</ncpoly>
		<ncpoly>h*x3-x3*h</ncpoly>
		<ncpoly>x5*x4-x4*x5</ncpoly>
		<ncpoly>x6*x4-x4*x6</ncpoly>
		<ncpoly>y1*x4-x4*y1+2*x3*h</ncpoly>
		<ncpoly>y2*x4-x4*y2</ncpoly>
		<ncpoly>y3*x4-x4*y3-2*x1*h</ncpoly>
		<ncpoly>y4*x4-x4*y4+2*H1*h+3*H2*h</ncpoly>
		<ncpoly>y5*x4-x4*y5-y1*h</ncpoly>
		<ncpoly>y6*x4-x4*y6+y3*h</ncpoly>
		<ncpoly>H1*x4-x4*H1-x4*h</ncpoly>
		<ncpoly>H2*x4-x4*H2</ncpoly>
		<ncpoly>h*x4-x4*h</ncpoly>
		<ncpoly>x6*x5-x5*x6</ncpoly>
		<ncpoly>y1*x5-x5*y1+x4*h</ncpoly>
		<ncpoly>y2*x5-x5*y2</ncpoly>
		<ncpoly>y3*x5-x5*y3</ncpoly>
		<ncpoly>y4*x5-x5*y4-x1*h</ncpoly>
		<ncpoly>y5*x5-x5*y5+H1*h+H2*h</ncpoly>
		<ncpoly>y6*x5-x5*y6-y2*h</ncpoly>
		<ncpoly>H1*x5-x5*H1-3*x5*h</ncpoly>
		<ncpoly>H2*x5-x5*H2+x5*h</ncpoly>
		<ncpoly>h*x5-x5*h</ncpoly>
		<ncpoly>y1*x6-x6*y1</ncpoly>
		<ncpoly>y2*x6-x6*y2+x5*h</ncpoly>
		<ncpoly>y3*x6-x6*y3-x4*h</ncpoly>
		<ncpoly>y4*x6-x6*y4+x3*h</ncpoly>
		<ncpoly>y5*x6-x6*y5-x2*h</ncpoly>
		<ncpoly>y6*x6-x6*y6+H1*h+2*H2*h</ncpoly>
		<ncpoly>H1*x6-x6*H1</ncpoly>
		<ncpoly>H2*x6-x6*H2-x6*h</ncpoly>
		<ncpoly>h*x6-x6*h</ncpoly>
		<ncpoly>y2*y1-y1*y2+y3*h</ncpoly>
		<ncpoly>y3*y1-y1*y3+2*y4*h</ncpoly>
		<ncpoly>y4*y1-y1*y4+3*y5*h</ncpoly>
		<ncpoly>y5*y1-y1*y5</ncpoly>
		<ncpoly>y6*y1-y1*y6</ncpoly>
		<ncpoly>H1*y1-y1*H1+2*y1*h</ncpoly>
		<ncpoly>H2*y1-y1*H2-y1*h</ncpoly>
		<ncpoly>h*y1-y1*h</ncpoly>
		<ncpoly>y3*y2-y2*y3</ncpoly>
		<ncpoly>y4*y2-y2*y4</ncpoly>
		<ncpoly>y5*y2-y2*y5+y6*h</ncpoly>
		<ncpoly>y6*y2-y2*y6</ncpoly>
		<ncpoly>H1*y2-y2*H1-3*y2*h</ncpoly>
		<ncpoly>H2*y2-y2*H2+2*y2*h</ncpoly>
		<ncpoly>h*y2-y2*h</ncpoly>
		<ncpoly>y4*y3-y3*y4-3*y6*h</ncpoly>
		<ncpoly>y5*y3-y3*y5</ncpoly>
		<ncpoly>y6*y3-y3*y6</ncpoly>
		<ncpoly>H1*y3-y3*H1-y3*h</ncpoly>
		<ncpoly>H2*y3-y3*H2+y3*h</ncpoly>
		<ncpoly>h*y3-y3*h</ncpoly>
		<ncpoly>y5*y4-y4*y5</ncpoly>
		<ncpoly>y6*y4-y4*y6</ncpoly>
		<ncpoly>H1*y4-y4*H1+y4*h</ncpoly>
		<ncpoly>H2*y4-y4*H2</ncpoly>
		<ncpoly>h*y4-y4*h</ncpoly>
		<ncpoly>y6*y5-y5*y6</ncpoly>
		<ncpoly>H1*y5-y5*H1+3*y5*h</ncpoly>
		<ncpoly>H2*y5-y5*H2-y5*h</ncpoly>
		<ncpoly>h*y5-y5*h</ncpoly>
		<ncpoly>H1*y6-y6*H1</ncpoly>
		<ncpoly>H2*y6-y6*H2+y6*h</ncpoly>
		<ncpoly>h*y6-y6*h</ncpoly>
		<ncpoly>H2*H1-H1*H2</ncpoly>
		<ncpoly>h*H1-H1*h</ncpoly>
		<ncpoly>h*H2-H2*h</ncpoly>
		<ncpoly>x1*x1*x1</ncpoly>
  </basis>
  <Comment>Semiautomatrically generated; the last generator makes life harder</Comment>
</FREEALGEBRA>
